flask_sse.py
Flask_SSE-1.0.0.dist-info/LICENSE
Flask_SSE-1.0.0.dist-info/METADATA
Flask_SSE-1.0.0.dist-info/WHEEL
Flask_SSE-1.0.0.dist-info/top_level.txt
Flask_SSE-1.0.0.dist-info/RECORD
