Metadata-Version: 1.1
Name: Flask-SSE
Version: 1.0.0
Summary: Server-Sent Events for Flask
Home-page: https://github.com/singingwolfboy/flask-sse
Author: David Baumgold
Author-email: david@davidbaumgold.com
License: MIT
Platform: UNKNOWN
Classifier: License :: OSI Approved :: MIT License
Classifier: Framework :: Flask
Classifier: Programming Language :: Python
Classifier: Programming Language :: Python :: 2.7
Classifier: Programming Language :: Python :: 3
Classifier: Programming Language :: Python :: 3.5
